{
  "id": "aboutus",
  "type": "SharedSlice",
  "name": "Aboutus",
  "description": "Aboutus",
  "variations": [
    {
      "id": "default",
      "name": "Default",
      "docURL": "...",
      "version": "initial",
      "description": "Default",
      "imageUrl": "",
      "primary": {
        "heading": {
          "type": "StructuredText",
          "config": {
            "label": "Heading",
            "placeholder": "",
            "allowTargetBlank": true,
            "single": "heading2"
          }
        },
        "image": {
          "type": "Image",
          "config": {
            "label": "Image",
            "constraint": {},
            "thumbnails": []
          }
        },
        "icon": {
          "type": "Select",
          "config": {
            "label": "Icon",
            "placeholder": "",
            "options": [
              "gear",
              "cycle"
            ]
          }
        },
        "subheading": {
          "type": "StructuredText",
          "config": {
            "label": "Subheading",
            "placeholder": "",
            "allowTargetBlank": true,
            "single": "heading3"
          }
        },
        "body": {
          "type": "StructuredText",
          "config": {
            "label": "Body",
            "placeholder": "",
            "allowTargetBlank": true,
            "single": "paragraph"
          }
        },
        "button_link": {
          "type": "Link",
          "config": {
            "label": "Button_Link",
            "placeholder": "",
            "select": null
          }
        },
        "button_text": {
          "type": "Text",
          "config": {
            "label": "Button Text",
            "placeholder": ""
          }
        }
      },
      "items": {}
    },
    {
      "id": "reverse",
      "name": "Reverse",
      "docURL": "...",
      "version": "initial",
      "description": "Default",
      "imageUrl": "",
      "primary": {
        "heading": {
          "type": "StructuredText",
          "config": {
            "label": "Heading",
            "placeholder": "",
            "allowTargetBlank": true,
            "single": "heading2"
          }
        },
        "image": {
          "type": "Image",
          "config": {
            "label": "Image",
            "constraint": {},
            "thumbnails": []
          }
        },
        "icon": {
          "type": "Select",
          "config": {
            "label": "Icon",
            "placeholder": "",
            "options": [
              "gear",
              "cycle"
            ]
          }
        },
        "subheading": {
          "type": "StructuredText",
          "config": {
            "label": "Subheading",
            "placeholder": "",
            "allowTargetBlank": true,
            "single": "heading3"
          }
        },
        "body": {
          "type": "StructuredText",
          "config": {
            "label": "Body",
            "placeholder": "",
            "allowTargetBlank": true,
            "single": "paragraph"
          }
        },
        "button_text": {
          "type": "StructuredText",
          "config": {
            "label": "Button Text",
            "placeholder": "",
            "allowTargetBlank": true,
            "multi": "paragraph,preformatted,heading1,heading2,heading3,heading4,heading5,heading6,strong,em,hyperlink,image,embed,list-item,o-list-item,rtl"
          }
        },
        "button_link": {
          "type": "Link",
          "config": {
            "label": "Button_Link",
            "placeholder": "",
            "select": null
          }
        }
      },
      "items": {}
    }
  ]
}